jupyterlab_widget_s3/__init__.py
jupyterlab_widget_s3/_version.py
jupyterlab_widget_s3/handlers.py
jupyterlab_widget_s3/labextension.zip
jupyterlab_widget_s3-0.1.0.data/data/etc/jupyter/jupyter_notebook_config.d/jupyterlab_widget_s3.json
jupyterlab_widget_s3-0.1.0.data/data/etc/jupyter/jupyter_server_config.d/jupyterlab_widget_s3.json
jupyterlab_widget_s3-0.1.0.data/data/share/jupyter/labextensions/jupyterlab_widget_s3/package.json
jupyterlab_widget_s3-0.1.0.data/data/share/jupyter/labextensions/jupyterlab_widget_s3/schemas/jupyterlab_widget_s3/package.json.orig
jupyterlab_widget_s3-0.1.0.data/data/share/jupyter/labextensions/jupyterlab_widget_s3/schemas/jupyterlab_widget_s3/plugin.json
jupyterlab_widget_s3-0.1.0.data/data/share/jupyter/labextensions/jupyterlab_widget_s3/static/144.988606679fc03963d88c.js
jupyterlab_widget_s3-0.1.0.data/data/share/jupyter/labextensions/jupyterlab_widget_s3/static/144.988606679fc03963d88c.js.LICENSE.txt
jupyterlab_widget_s3-0.1.0.data/data/share/jupyter/labextensions/jupyterlab_widget_s3/static/742.76898966258e65115eff.js
jupyterlab_widget_s3-0.1.0.data/data/share/jupyter/labextensions/jupyterlab_widget_s3/static/760.90f3aad1a1cd6eacad51.js
jupyterlab_widget_s3-0.1.0.data/data/share/jupyter/labextensions/jupyterlab_widget_s3/static/776.6083de03962d8e36b935.js
jupyterlab_widget_s3-0.1.0.data/data/share/jupyter/labextensions/jupyterlab_widget_s3/static/978.5f108aadf37402691478.js
jupyterlab_widget_s3-0.1.0.data/data/share/jupyter/labextensions/jupyterlab_widget_s3/static/978.5f108aadf37402691478.js.LICENSE.txt
jupyterlab_widget_s3-0.1.0.data/data/share/jupyter/labextensions/jupyterlab_widget_s3/static/jupyterlab_widget_s3.da7c40380fe94cf7aada.css
jupyterlab_widget_s3-0.1.0.data/data/share/jupyter/labextensions/jupyterlab_widget_s3/static/jupyterlab_widget_s3.f837567d75328e710a40.css
jupyterlab_widget_s3-0.1.0.data/data/share/jupyter/labextensions/jupyterlab_widget_s3/static/remoteEntry.1bbb7f7a74d952cdfdb4.js
jupyterlab_widget_s3-0.1.0.dist-info/METADATA
jupyterlab_widget_s3-0.1.0.dist-info/WHEEL
jupyterlab_widget_s3-0.1.0.dist-info/licenses/LICENSE
jupyterlab_widget_s3-0.1.0.dist-info/RECORD
