Metadata-Version: 2.1
Name: jupyterlab_widget_s3
Version: 0.1.0
Summary: Jupyterlab 插件
Project-URL: Homepage, http://60.60.60.146:8091/zhuying/jupyterlab_plugins/-/tree/master/jupyterlab_widget_s3
Project-URL: Bug Tracker, http://60.60.60.146:8091/zhuying/jupyterlab_plugins/-/tree/master/jupyterlab_widget_s3/issues
Project-URL: Repository, http://60.60.60.146:8091/zhuying/jupyterlab_plugins/-/tree/master/jupyterlab_widget_s3.git
Author-email: dfc <me@test.com>
License: BSD 3-Clause License
License-File: LICENSE
Classifier: Framework :: Jupyter
Classifier: Framework :: Jupyter :: JupyterLab
Classifier: Framework :: Jupyter :: JupyterLab :: 3
Classifier: Framework :: Jupyter :: JupyterLab :: Extensions
Classifier: Framework :: Jupyter :: JupyterLab :: Extensions :: Prebuilt
Classifier: License :: OSI Approved :: BSD License
Classifier: Programming Language :: Python
Classifier: Programming Language :: Python :: 3
Classifier: Programming Language :: Python :: 3.7
Classifier: Programming Language :: Python :: 3.8
Classifier: Programming Language :: Python :: 3.9
Classifier: Programming Language :: Python :: 3.10
Classifier: Programming Language :: Python :: 3.11
Requires-Python: >=3.7
Requires-Dist: jupyter-server<3,>=1.21
